MANIFEST.in
README.md
setup.cfg
setup.py
clustergrammer_gl/__init__.py
clustergrammer_gl/_version.py
clustergrammer_gl/example.py
clustergrammer_gl.egg-info/PKG-INFO
clustergrammer_gl.egg-info/SOURCES.txt
clustergrammer_gl.egg-info/dependency_links.txt
clustergrammer_gl.egg-info/not-zip-safe
clustergrammer_gl.egg-info/requires.txt
clustergrammer_gl.egg-info/top_level.txt
clustergrammer_gl/clustergrammer/__init__.py
clustergrammer_gl/clustergrammer/calc_clust.py
clustergrammer_gl/clustergrammer/cat_pval.py
clustergrammer_gl/clustergrammer/categories.py
clustergrammer_gl/clustergrammer/data_formats.py
clustergrammer_gl/clustergrammer/downsample_fun.py
clustergrammer_gl/clustergrammer/enrichr_functions.py
clustergrammer_gl/clustergrammer/export_data.py
clustergrammer_gl/clustergrammer/iframe_web_app.py
clustergrammer_gl/clustergrammer/initialize_net.py
clustergrammer_gl/clustergrammer/load_data.py
clustergrammer_gl/clustergrammer/load_vect_post.py
clustergrammer_gl/clustergrammer/make_clust_fun.py
clustergrammer_gl/clustergrammer/make_sim_mat.py
clustergrammer_gl/clustergrammer/make_unique_labels.py
clustergrammer_gl/clustergrammer/make_views.py
clustergrammer_gl/clustergrammer/make_viz.py
clustergrammer_gl/clustergrammer/normalize_fun.py
clustergrammer_gl/clustergrammer/proc_df_labels.py
clustergrammer_gl/clustergrammer/run_filter.py
clustergrammer_gl/static/extension.js
clustergrammer_gl/static/f2c72c12e473db657b6f061871c24289.png
clustergrammer_gl/static/index.js
clustergrammer_gl/static/index.js.map